Mongo/Mongo.py
Mongo/__init__.py
pyqudie/Mongo.py
pyqudie/MongoExceptions.py
pyqudie/__init__.py
pyqudie-0.0.5.dist-info/DESCRIPTION.rst
pyqudie-0.0.5.dist-info/METADATA
pyqudie-0.0.5.dist-info/RECORD
pyqudie-0.0.5.dist-info/WHEEL
pyqudie-0.0.5.dist-info/metadata.json
pyqudie-0.0.5.dist-info/top_level.txt
test/__init__.py
test/test_ObjectId2String.py
test/test_ObjectId2UnixTimeStamp.py
test/test_String2ObjectId.py
test/test_find.py
test/test_init.py
test/test_insert.py
test/test_remove.py
test/test_update.py
test/testconfig.py
