Metadata-Version: 2.0
Name: pyqudie
Version: 0.0.5
Summary: kqudie python edition
Home-page: https://github.com/evi0s/pyqudie
Author: evi0s<wc810267705@163.com>
Author-email: wc810267705@163.com
License: UNKNOWN
Keywords: mongodb
Platform: UNKNOWN
Classifier: Environment :: Console
Classifier: Programming Language :: Python :: 2.7
Classifier: Topic :: Internet :: WWW/HTTP
Classifier: Topic :: Software Development :: Libraries :: Python Modules
Requires-Dist: pymongo (>=3.7.2)
